queue_az/__init__.py
queue_az/config/__init__.py
queue_az/config/config.py
queue_az/errors/__init__.py
queue_az/errors/errors.py
queue_az/msg/__init__.py
queue_az/msg/messages.py
queue_az/queues/__init__.py
queue_az/queues/queues.py
queue_az/util/__init__.py
queue_az/util/util.py
queue_az-0.1.0.dist-info/METADATA
queue_az-0.1.0.dist-info/WHEEL
queue_az-0.1.0.dist-info/top_level.txt
queue_az-0.1.0.dist-info/RECORD
