Metadata-Version: 2.1
Name: queue-az
Version: 0.1.0
Summary: Async Python SDK for Azure Queue Storage
Author-email: Marcel Claramunt <marcel@moveread.com>
Project-URL: home, https://github.com/moveread/azure-sdks/tree/main/sdks/queue-az
Project-URL: repo, https://github.com/moveread/azure-sdks
Requires-Python: >=3.10
Requires-Dist: azure-storage-queue
Requires-Dist: aiohttp
